passit/__init__.py
passit/__main__.py
passit/constants.py
passit/passit.py
passit-0.2.2.dist-info/LICENSE
passit-0.2.2.dist-info/METADATA
passit-0.2.2.dist-info/WHEEL
passit-0.2.2.dist-info/entry_points.txt
passit-0.2.2.dist-info/top_level.txt
passit-0.2.2.dist-info/RECORD
