Metadata-Version: 2.1
Name: passit
Version: 0.2.2
Summary: Strong key generator
Home-page: https://github.com/capriciousaton/passit
Author: Brian Thompson
Author-email: brian.thompson@hashvault.io
License: MIT
Platform: UNKNOWN
Classifier: License :: OSI Approved :: MIT License
Classifier: Programming Language :: Python :: 3
Classifier: Programming Language :: Python :: 3.6
